richui/__init__.py
richui/config.py
richui/example.py
richui/richui.py
richui/utils.py
richui-0.0.3.dist-info/METADATA
richui-0.0.3.dist-info/WHEEL
richui-0.0.3.dist-info/top_level.txt
richui-0.0.3.dist-info/RECORD
