Metadata-Version: 2.4
Name: richui
Version: 0.0.3
Summary: An interactive command-line UI module built on top of Rich for customizable UI components.
Home-page: https://pypi.org/project/richui
Author: Moh Iqbal Hidayat
Author-email: Moh Iqbal Hidayat <iqbalmh18.dev@gmail.com>
Project-URL: Homepage, https://pypi.org/project/richui
Project-URL: Source, https://github.com/iqbalmh18/richui
Keywords: rich,richui,cli,UI,interactive,terminal
Classifier: Programming Language :: Python :: 3
Classifier: License :: OSI Approved :: MIT License
Classifier: Operating System :: OS Independent
Requires-Python: >=3.7
Requires-Dist: rich
Dynamic: author
Dynamic: home-page
Dynamic: requires-python
